<?xml version='1.0' encoding='UTF-8'?>
<object id="6CHqoyiGrfND" classes="section" acceptedChildren=":Proteus-any" acceptedParents=":Proteus-document section">
  <properties>
    <stringProperty name=":Proteus-name" category="general"><![CDATA[Diagramas de navegación del sistema]]></stringProperty>
    <markdownProperty name="comments" category="general"><![CDATA[]]></markdownProperty>
  </properties>
  <children>
    <child id="4VBd9ZC9t3Jo"/>
    <child id="5PAKySQezLib"/>
    <child id="5aFeGXuxAuTu"/>
    <child id="6pNBCSqwez52"/>
    <child id="54yfGEk9umhm"/>
    <child id="bQTC5jgRQjrg"/>
    <child id="3qVLQTMs3Yak"/>
    <child id="7Mrqs5TB5ubC"/>
    <child id="3HGV5NzbsQhJ"/>
    <child id="4pWMsyKgBV6P"/>
    <child id="4fPRxX2Renbn"/>
  </children>
</object>
