<?xml version='1.0' encoding='UTF-8'?>
<object id="82K3uzDEe6QK" classes="attribute" acceptedChildren=":Proteus-none" acceptedParents="entity-class association">
  <properties>
    <stringProperty name=":Proteus-name" category="general"><![CDATA[contraseña]]></stringProperty>
    <stringProperty name="type" category="general"><![CDATA[string]]></stringProperty>
    <markdownProperty name="description" category="detail"><![CDATA[Código alfanumérico que permite al usuario iniciar sesión en el sistema]]></markdownProperty>
    <markdownProperty name="comments" category="comments"><![CDATA[]]></markdownProperty>
  </properties>
  <children/>
</object>
